multivaluefield.py
django_multivalueformfield-0.0.2.dist-info/DESCRIPTION.rst
django_multivalueformfield-0.0.2.dist-info/METADATA
django_multivalueformfield-0.0.2.dist-info/RECORD
django_multivalueformfield-0.0.2.dist-info/WHEEL
django_multivalueformfield-0.0.2.dist-info/metadata.json
django_multivalueformfield-0.0.2.dist-info/top_level.txt
