Metadata-Version: 2.0
Name: django-multivalueformfield
Version: 0.0.2
Summary: Multiple-value field for Django forms
Home-page: https://github.com/ukch/django_multivalueformfield
Author: Joel Cross
Author-email: joel@kazbak.co.uk
License: MIT
Platform: UNKNOWN
Classifier: Development Status :: 4 - Beta
Classifier: Intended Audience :: Developers
Classifier: License :: OSI Approved :: MIT License
Classifier: Programming Language :: Python :: 3.6
Classifier: Framework :: Django :: 2.0
Requires-Dist: Django (>=2.0)
